{
    "user_badges":[],
    "user":{
        "id":9923,
        "username":"IsabelSchoepd",
        "name":"Isabel Schöps (Vitalik Buterin)",
        "avatar_template":"/user_avatar/ethresear.ch/isabelschoepd/{size}/12790_2.png",
        "email":"si_foundation@icloud.com",
        "secondary_emails":[],
        "unconfirmed_emails":[],
        "last_posted_at":null,
        "last_seen_at":"2023-08-01T22:24:54.079Z",
        "created_at":"2023-08-01T22:23:37.910Z",
        "ignored":false,
        "muted":false,
        "can_ignore_user":false,
        "can_mute_user":false,
        "can_send_private_messages":false,
        "can_send_private_message_to_user":false,
        "trust_level":0,
        "moderator":false,
        "admin":false,
        "title":null,
        "badge_count":0,
        "user_fields":{
            "1":"ethereum.org",
            "2":"github.com"
        },
        "custom_fields":{},
        "time_read":0,
        "recent_time_read":0,
        "primary_group_id":null,
        "primary_group_name":null,
        "flair_group_id":null,
        "flair_name":null,
        "flair_url":null,
        "flair_bg_color":null,
        "flair_color":null,
        "featured_topic":null,
        "pending_posts_count":0,
        "can_edit":true,
        "can_edit_username":false,
        "can_edit_email":true,
        "can_edit_name":true,
        "uploaded_avatar_id":12790,
        "has_title_badges":false,
        "pending_count":0,
        "profile_view_count":0,
        "second_factor_enabled":false,
        "second_factor_backup_enabled":false,
        "associated_accounts":[
            {
                "name":"github",
                "description":"si_foundation@icloud.com"
            }
        ],
        "can_upload_profile_header":true,
        "can_upload_user_card_background":true,
        "locale":"en",
        "muted_category_ids":[],
        "regular_category_ids":[],
        "watched_tags":[],
        "watching_first_post_tags":[],
        "tracked_tags":[],
        "muted_tags":[],
        "tracked_category_ids":[],
        "watched_category_ids":[],
        "watched_first_post_category_ids":[
            3
        ],
        "system_avatar_upload_id":null,
        "system_avatar_template":"/letter_avatar_proxy/v4/letter/i/dec6dc/{size}.png",
        "custom_avatar_upload_id":12790,
        "custom_avatar_template":"/user_avatar/ethresear.ch/isabelschoepd/{size}/12790_2.png",
        "muted_usernames":[],
        "ignored_usernames":[],
        "allowed_pm_usernames":[],
        "mailing_list_posts_per_day":4,
        "can_change_bio":true,
        "can_change_location":true,
        "can_change_website":true,
        "can_change_tracking_preferences":true,
        "user_api_keys":null,
        "user_auth_tokens":[
            {
                "id":20957,
                "client_ip":"93.230.153.97",
                "location":"unknown",
                "browser":"unknown browser",
                "device":"iPhone",
                "os":"iOS",
                "icon":"fab-apple",
                "created_at":"2023-08-01T22:23:38.029Z",
                "seen_at":"2023-08-01T22:23:38.827Z"
            }
        ],
        "user_notification_schedule":{
            "enabled":false,
            "day_0_start_time":480,
            "day_0_end_time":1020,
            "day_1_start_time":480,
            "day_1_end_time":1020,
            "day_2_start_time":480,
            "day_2_end_time":1020,
            "day_3_start_time":480,
            "day_3_end_time":1020,
            "day_4_start_time":480,
            "day_4_end_time":1020,
            "day_5_start_time":480,
            "day_5_end_time":1020,
            "day_6_start_time":480,
            "day_6_end_time":1020
        },
        "use_logo_small_as_avatar":false,
        "featured_user_badge_ids":[],
        "invited_by":null,
        "groups":[
            {
                "id":10,
                "automatic":true,
                "name":"trust_level_0",
                "display_name":"trust_level_0",
                "user_count":6560,
                "mentionable_level":0,
                "messageable_level":0,
                "visibility_level":1,
                "primary_group":false,
                "title":null,
                "grant_trust_level":null,
                "has_messages":false,
                "flair_url":null,
                "flair_bg_color":null,
                "flair_color":null,
                "bio_cooked":null,
                "bio_excerpt":null,
                "public_admission":false,
                "public_exit":false,
                "allow_membership_requests":false,
                "full_name":null,
                "default_notification_level":3,
                "membership_request_template":null,
                "members_visibility_level":0,
                "can_see_members":true,
                "publish_read_state":false
            }
        ],
        "group_users":[
            {
                "group_id":10,
                "user_id":9923,
                "notification_level":3,
                "owner":false
            }
        ],
        "user_option":{
            "user_id":9923,
            "mailing_list_mode":false,
            "mailing_list_mode_frequency":1,
            "email_digests":true,
            "email_level":1,
            "email_messages_level":0,
            "external_links_in_new_tab":false,
            "color_scheme_id":null,
            "dark_scheme_id":null,
            "dynamic_favicon":true,
            "enable_quoting":true,
            "enable_defer":false,
            "digest_after_minutes":10080,
            "automatically_unpin_topics":true,
            "auto_track_topics_after_msecs":240000,
            "notification_level_when_replying":2,
            "new_topic_duration_minutes":2880,
            "email_previous_replies":2,
            "email_in_reply_to":false,
            "like_notification_frequency":1,
            "include_tl0_in_digests":false,
            "theme_ids":[
                2
            ],
            "theme_key_seq":0,
            "allow_private_messages":true,
            "enable_allowed_pm_users":false,
            "homepage_id":null,
            "hide_profile_and_presence":false,
            "text_size":"normal",
            "text_size_seq":0,
            "title_count_mode":"notifications",
            "timezone":"Europe/Berlin",
            "skip_new_user_tips":true,
            "default_calendar":"none_selected",
            "oldest_search_log_date":null
        }
    }
}
